Metadata-Version: 2.1
Name: clustaar.schemas
Version: 1.10.0
Summary: Clustaar objects schemas
Home-page: https://github.com/Clustaar/clustaar.schemas
Author: Aurélien
Author-email: aurelien@clustaar.com
License: mit
Platform: any
Classifier: Development Status :: 4 - Beta
Classifier: Programming Language :: Python
License-File: LICENSE.txt
License-File: AUTHORS.rst
Requires-Dist: lupin~=2.0.0
Requires-Dist: bleach==5.0.1
